{
    "serverIp": "127.0.0.1",
    "serverNetId": "127.0.0.1.1.1",
    "localNetId": "127.0.0.1.1.20",
    "adsPort": 851,
    "variableName": "",
    "variableType": "int32",
    "adsVariables": {
        "rotaryTable": {
            "actualPosition": {
                "name": "Table Motor (AX8108-0000-0105).Ch A.Ch A Interpolator Outputs",
                "type": "double"
            },
            "sensor0": {
                "name": "8 Dig In (EL1008).Channel 1",
                "type": "bool"
            },
            "sensor180": {
                "name": "8 Dig In (EL1008).Channel 2",
                "type": "bool"
            }
        },
        "conveyor": {
            "run": {
                "name": "8 Dig Out (EL2008).Channel 1",
                "type": "bool"
            },
            "sensor1": {
                "name": "8 Dig In (EL1008).Channel 3",
                "type": "bool"
            },
            "sensor2": {
                "name": "8 Dig In (EL1008).Channel 4",
                "type": "bool"
            },
            "sensor3": {
                "name": "8 Dig In (EL1008).Channel 5",
                "type": "bool"
            },
            "sensor4": {
                "name": "8 Dig In (EL1008).Channel 6",
                "type": "bool"
            },
            "damperDownSensor": {
                "name": "8 Dig In (EL1008).Channel 7",
                "type": "bool"
            },
            "damperUpSensor": {
                "name": "8 Dig In (EL1008).Channel 8",
                "type": "bool"
            },
            "damperMoveDown": {
                "name": "8 Dig Out (EL2008).Channel 2",
                "type": "bool"
            },
            "damperMoveUp": {
                "name": "8 Dig Out (EL2008).Channel 3",
                "type": "bool"
            }
        },
        "robot": {
            "jobId": {
                "name": "MAIN.JobId",
                "type": "int32"
            },
            "areaFreePLC1": {
                "name": "MAIN.AreaFreePLC1",
                "type": "bool"
            },
            "areaFreePLC2": {
                "name": "MAIN.AreaFreePLC2",
                "type": "bool"
            },
            "areaFreePLC3": {
                "name": "MAIN.AreaFreePLC3",
                "type": "bool"
            },
            "areaFreePLC4": {
                "name": "MAIN.AreaFreePLC4",
                "type": "bool"
            },
            "actualJobId": {
                "name": "MAIN.actualJobId",
                "type": "int32"
            },
            "gripperSensor": {
                "name": "MAIN.GripperSensor",
                "type": "bool"
            },
            "areaFreeRobot1": {
                "name": "MAIN.AreaFreeRobot1",
                "type": "bool"
            },
            "areaFreeRobot2": {
                "name": "MAIN.AreaFreeRobot2",
                "type": "bool"
            },
            "areaFreeRobot3": {
                "name": "MAIN.AreaFreeRobot3",
                "type": "bool"
            },
            "areaFreeRobot4": {
                "name": "MAIN.AreaFreeRobot4",
                "type": "bool"
            }
        }
    }
}